{
    "description": "",
    "tags": [],
    "size": {
        "height": 4032,
        "width": 3024
    },
    "objects": [
        {
            "id": 14428956,
            "classId": 20791,
            "description": "",
            "geometryType": "polygon",
            "labelerLogin": "gr@datasetninja.com",
            "createdAt": "2023-07-11T11:58:02.997Z",
            "updatedAt": "2023-07-11T11:58:02.997Z",
            "tags": [],
            "classTitle": "b_green",
            "points": {
                "exterior": [
                    [
                        12,
                        357
                    ],
                    [
                        73,
                        393
                    ],
                    [
                        146,
                        414
                    ],
                    [
                        216,
                        420
                    ],
                    [
                        360,
                        367
                    ],
                    [
                        430,
                        309
                    ],
                    [
                        473,
                        247
                    ],
                    [
                        489,
                        136
                    ],
                    [
                        477,
                        80
                    ],
                    [
                        462,
                        7
                    ],
                    [
                        455,
                        3
                    ],
                    [
                        319,
                        1
                    ],
                    [
                        117,
                        1
                    ],
                    [
                        1,
                        0
                    ],
                    [
                        1,
                        290
                    ],
                    [
                        3,
                        353
                    ]
                ],
                "interior": []
            }
        },
        {
            "id": 14428955,
            "classId": 20791,
            "description": "",
            "geometryType": "polygon",
            "labelerLogin": "gr@datasetninja.com",
            "createdAt": "2023-07-11T11:58:02.995Z",
            "updatedAt": "2023-07-11T11:58:02.995Z",
            "tags": [],
            "classTitle": "b_green",
            "points": {
                "exterior": [
                    [
                        1245,
                        2671
                    ],
                    [
                        1287,
                        2635
                    ],
                    [
                        1337,
                        2618
                    ],
                    [
                        1382,
                        2619
                    ],
                    [
                        1427,
                        2634
                    ],
                    [
                        1473,
                        2683
                    ],
                    [
                        1501,
                        2756
                    ],
                    [
                        1512,
                        2810
                    ],
                    [
                        1503,
                        2852
                    ],
                    [
                        1488,
                        2890
                    ],
                    [
                        1458,
                        2915
                    ],
                    [
                        1385,
                        2957
                    ],
                    [
                        1323,
                        2962
                    ],
                    [
                        1279,
                        2955
                    ],
                    [
                        1233,
                        2930
                    ],
                    [
                        1202,
                        2888
                    ],
                    [
                        1189,
                        2841
                    ],
                    [
                        1177,
                        2802
                    ],
                    [
                        1189,
                        2764
                    ],
                    [
                        1213,
                        2715
                    ]
                ],
                "interior": []
            }
        },
        {
            "id": 14428954,
            "classId": 20790,
            "description": "",
            "geometryType": "polygon",
            "labelerLogin": "gr@datasetninja.com",
            "createdAt": "2023-07-11T11:58:02.995Z",
            "updatedAt": "2023-07-11T11:58:02.995Z",
            "tags": [],
            "classTitle": "b_half_ripened",
            "points": {
                "exterior": [
                    [
                        1569,
                        2587
                    ],
                    [
                        1609,
                        2545
                    ],
                    [
                        1692,
                        2530
                    ],
                    [
                        1733,
                        2538
                    ],
                    [
                        1787,
                        2576
                    ],
                    [
                        1835,
                        2624
                    ],
                    [
                        1892,
                        2713
                    ],
                    [
                        1898,
                        2758
                    ],
                    [
                        1892,
                        2788
                    ],
                    [
                        1872,
                        2822
                    ],
                    [
                        1858,
                        2857
                    ],
                    [
                        1847,
                        2886
                    ],
                    [
                        1811,
                        2916
                    ],
                    [
                        1754,
                        2944
                    ],
                    [
                        1718,
                        2952
                    ],
                    [
                        1667,
                        2944
                    ],
                    [
                        1617,
                        2930
                    ],
                    [
                        1583,
                        2909
                    ],
                    [
                        1559,
                        2886
                    ],
                    [
                        1532,
                        2845
                    ],
                    [
                        1509,
                        2754
                    ],
                    [
                        1509,
                        2704
                    ],
                    [
                        1525,
                        2652
                    ],
                    [
                        1548,
                        2620
                    ]
                ],
                "interior": []
            }
        },
        {
            "id": 14428953,
            "classId": 20790,
            "description": "",
            "geometryType": "polygon",
            "labelerLogin": "gr@datasetninja.com",
            "createdAt": "2023-07-11T11:58:02.995Z",
            "updatedAt": "2023-07-11T11:58:02.995Z",
            "tags": [],
            "classTitle": "b_half_ripened",
            "points": {
                "exterior": [
                    [
                        2749,
                        2871
                    ],
                    [
                        2623,
                        2893
                    ],
                    [
                        2517,
                        2951
                    ],
                    [
                        2468,
                        3055
                    ],
                    [
                        2479,
                        3149
                    ],
                    [
                        2529,
                        3228
                    ],
                    [
                        2564,
                        3303
                    ],
                    [
                        2662,
                        3390
                    ],
                    [
                        2773,
                        3421
                    ],
                    [
                        2857,
                        3428
                    ],
                    [
                        2860,
                        3360
                    ],
                    [
                        2815,
                        3322
                    ],
                    [
                        2799,
                        3275
                    ],
                    [
                        2796,
                        3217
                    ],
                    [
                        2796,
                        3170
                    ],
                    [
                        2822,
                        3123
                    ],
                    [
                        2815,
                        3099
                    ],
                    [
                        2796,
                        3066
                    ],
                    [
                        2796,
                        3024
                    ],
                    [
                        2796,
                        2949
                    ],
                    [
                        2780,
                        2928
                    ],
                    [
                        2749,
                        2902
                    ]
                ],
                "interior": []
            }
        },
        {
            "id": 14428952,
            "classId": 20791,
            "description": "",
            "geometryType": "polygon",
            "labelerLogin": "gr@datasetninja.com",
            "createdAt": "2023-07-11T11:58:02.994Z",
            "updatedAt": "2023-07-11T11:58:02.994Z",
            "tags": [],
            "classTitle": "b_green",
            "points": {
                "exterior": [
                    [
                        2529,
                        848
                    ],
                    [
                        2578,
                        869
                    ],
                    [
                        2641,
                        930
                    ],
                    [
                        2672,
                        1019
                    ],
                    [
                        2667,
                        1089
                    ],
                    [
                        2620,
                        1179
                    ],
                    [
                        2545,
                        1237
                    ],
                    [
                        2416,
                        1251
                    ],
                    [
                        2299,
                        1204
                    ],
                    [
                        2242,
                        1153
                    ],
                    [
                        2237,
                        1057
                    ],
                    [
                        2254,
                        972
                    ],
                    [
                        2294,
                        920
                    ],
                    [
                        2334,
                        885
                    ],
                    [
                        2409,
                        873
                    ],
                    [
                        2479,
                        843
                    ]
                ],
                "interior": []
            }
        },
        {
            "id": 14428951,
            "classId": 20791,
            "description": "",
            "geometryType": "polygon",
            "labelerLogin": "gr@datasetninja.com",
            "createdAt": "2023-07-11T11:58:02.994Z",
            "updatedAt": "2023-07-11T11:58:02.994Z",
            "tags": [],
            "classTitle": "b_green",
            "points": {
                "exterior": [
                    [
                        2510,
                        838
                    ],
                    [
                        2620,
                        735
                    ],
                    [
                        2653,
                        629
                    ],
                    [
                        2648,
                        493
                    ],
                    [
                        2597,
                        366
                    ],
                    [
                        2496,
                        289
                    ],
                    [
                        2385,
                        277
                    ],
                    [
                        2306,
                        301
                    ],
                    [
                        2233,
                        345
                    ],
                    [
                        2176,
                        390
                    ],
                    [
                        2115,
                        474
                    ],
                    [
                        2097,
                        580
                    ],
                    [
                        2129,
                        723
                    ],
                    [
                        2183,
                        829
                    ],
                    [
                        2235,
                        864
                    ],
                    [
                        2334,
                        885
                    ],
                    [
                        2404,
                        873
                    ],
                    [
                        2482,
                        833
                    ]
                ],
                "interior": []
            }
        },
        {
            "id": 14428950,
            "classId": 20789,
            "description": "",
            "geometryType": "polygon",
            "labelerLogin": "gr@datasetninja.com",
            "createdAt": "2023-07-11T11:58:02.994Z",
            "updatedAt": "2023-07-11T11:58:02.994Z",
            "tags": [],
            "classTitle": "b_fully_ripened",
            "points": {
                "exterior": [
                    [
                        2014,
                        1850
                    ],
                    [
                        2115,
                        1895
                    ],
                    [
                        2202,
                        1982
                    ],
                    [
                        2268,
                        2104
                    ],
                    [
                        2303,
                        2245
                    ],
                    [
                        2275,
                        2463
                    ],
                    [
                        2207,
                        2648
                    ],
                    [
                        2083,
                        2787
                    ],
                    [
                        1913,
                        2860
                    ],
                    [
                        1702,
                        2895
                    ],
                    [
                        1580,
                        2857
                    ],
                    [
                        1479,
                        2801
                    ],
                    [
                        1336,
                        2735
                    ],
                    [
                        1256,
                        2688
                    ],
                    [
                        1186,
                        2554
                    ],
                    [
                        1143,
                        2430
                    ],
                    [
                        1132,
                        2256
                    ],
                    [
                        1214,
                        2087
                    ],
                    [
                        1296,
                        2005
                    ],
                    [
                        1357,
                        1975
                    ],
                    [
                        1432,
                        1958
                    ],
                    [
                        1488,
                        1928
                    ],
                    [
                        1559,
                        1916
                    ],
                    [
                        1613,
                        1916
                    ],
                    [
                        1686,
                        1860
                    ],
                    [
                        1798,
                        1817
                    ],
                    [
                        1902,
                        1817
                    ]
                ],
                "interior": []
            }
        },
        {
            "id": 14428949,
            "classId": 20789,
            "description": "",
            "geometryType": "polygon",
            "labelerLogin": "gr@datasetninja.com",
            "createdAt": "2023-07-11T11:58:02.994Z",
            "updatedAt": "2023-07-11T11:58:02.994Z",
            "tags": [],
            "classTitle": "b_fully_ripened",
            "points": {
                "exterior": [
                    [
                        1101,
                        1829
                    ],
                    [
                        991,
                        1914
                    ],
                    [
                        934,
                        2057
                    ],
                    [
                        913,
                        2174
                    ],
                    [
                        932,
                        2268
                    ],
                    [
                        979,
                        2360
                    ],
                    [
                        1031,
                        2395
                    ],
                    [
                        1146,
                        2432
                    ],
                    [
                        1132,
                        2261
                    ],
                    [
                        1211,
                        2090
                    ],
                    [
                        1298,
                        2000
                    ],
                    [
                        1357,
                        1972
                    ],
                    [
                        1427,
                        1951
                    ],
                    [
                        1317,
                        1949
                    ],
                    [
                        1214,
                        1909
                    ],
                    [
                        1108,
                        1827
                    ]
                ],
                "interior": []
            }
        },
        {
            "id": 14428948,
            "classId": 20789,
            "description": "",
            "geometryType": "polygon",
            "labelerLogin": "gr@datasetninja.com",
            "createdAt": "2023-07-11T11:58:02.993Z",
            "updatedAt": "2023-07-11T11:58:02.993Z",
            "tags": [],
            "classTitle": "b_fully_ripened",
            "points": {
                "exterior": [
                    [
                        1773,
                        1817
                    ],
                    [
                        1885,
                        1681
                    ],
                    [
                        1920,
                        1622
                    ],
                    [
                        1932,
                        1543
                    ],
                    [
                        1993,
                        1395
                    ],
                    [
                        1991,
                        1258
                    ],
                    [
                        1979,
                        1120
                    ],
                    [
                        1895,
                        944
                    ],
                    [
                        1824,
                        841
                    ],
                    [
                        1604,
                        740
                    ],
                    [
                        1385,
                        730
                    ],
                    [
                        1202,
                        810
                    ],
                    [
                        1049,
                        918
                    ],
                    [
                        951,
                        1026
                    ],
                    [
                        876,
                        1181
                    ],
                    [
                        864,
                        1329
                    ],
                    [
                        873,
                        1453
                    ],
                    [
                        932,
                        1622
                    ],
                    [
                        1056,
                        1787
                    ],
                    [
                        1103,
                        1817
                    ],
                    [
                        1218,
                        1914
                    ],
                    [
                        1319,
                        1946
                    ],
                    [
                        1430,
                        1951
                    ],
                    [
                        1561,
                        1916
                    ],
                    [
                        1629,
                        1890
                    ],
                    [
                        1686,
                        1855
                    ]
                ],
                "interior": []
            }
        }
    ]
}